moat/lib/victron/__init__.py
moat/lib/victron/dbus/__init__.py
moat/lib/victron/dbus/monitor.py
moat/lib/victron/dbus/utils.py
moat_lib_victron-0.1.5.dist-info/licenses/LICENSE.txt
moat_lib_victron-0.1.5.dist-info/METADATA
moat_lib_victron-0.1.5.dist-info/WHEEL
moat_lib_victron-0.1.5.dist-info/top_level.txt
moat_lib_victron-0.1.5.dist-info/RECORD
